[
  {
    "category": "Large Cap Fund",
    "latest_date": "2026-04-23",
    "return_1d": -0.94,
    "return_1w": 0.25,
    "return_1m": 8.7,
    "return_3m": -0.95,
    "return_6m": -4.3,
    "return_1y": 2.36,
    "return_2y": 6.14,
    "return_3y": 15.44,
    "return_5y": 13.9,
    "return_10y": 13.65
  },
  {
    "category": "Mid Cap Fund",
    "latest_date": "2026-04-23",
    "return_1d": -0.35,
    "return_1w": 1.91,
    "return_1m": 13.59,
    "return_3m": 6.39,
    "return_6m": 0.3,
    "return_1y": 10.83,
    "return_2y": 11.33,
    "return_3y": 23.83,
    "return_5y": 20.39,
    "return_10y": 17.59
  },
  {
    "category": "Small Cap Fund",
    "latest_date": "2026-04-23",
    "return_1d": -0.34,
    "return_1w": 2.35,
    "return_1m": 15.78,
    "return_3m": 9.16,
    "return_6m": -1.11,
    "return_1y": 8.47,
    "return_2y": 7.91,
    "return_3y": 21.4,
    "return_5y": 21.27,
    "return_10y": 18.34
  },
  {
    "category": "Flexi Cap Fund",
    "latest_date": "2026-04-23",
    "return_1d": -0.73,
    "return_1w": 0.72,
    "return_1m": 10.64,
    "return_3m": 1.43,
    "return_6m": -3.52,
    "return_1y": 4.04,
    "return_2y": 6.99,
    "return_3y": 17.41,
    "return_5y": 15.37,
    "return_10y": 15.07
  },
  {
    "category": "Multi Cap Fund",
    "latest_date": "2026-04-23",
    "return_1d": -0.56,
    "return_1w": 1.29,
    "return_1m": 12.03,
    "return_3m": 3.93,
    "return_6m": -2.3,
    "return_1y": 6.43,
    "return_2y": 8.52,
    "return_3y": 20.47,
    "return_5y": 19.03,
    "return_10y": 16.45
  },
  {
    "category": "Large & Mid Cap fund",
    "latest_date": "2026-04-23",
    "return_1d": -0.58,
    "return_1w": 1.05,
    "return_1m": 10.73,
    "return_3m": 2.34,
    "return_6m": -2.36,
    "return_1y": 6,
    "return_2y": 8.6,
    "return_3y": 19.6,
    "return_5y": 17.44,
    "return_10y": 15.59
  },
  {
    "category": "Value Fund",
    "latest_date": "2026-04-23",
    "return_1d": -0.74,
    "return_1w": 0.88,
    "return_1m": 10.67,
    "return_3m": 2.66,
    "return_6m": -0.17,
    "return_1y": 7.77,
    "return_2y": 7.49,
    "return_3y": 20.27,
    "return_5y": 17.97,
    "return_10y": 15.54
  },
  {
    "category": "Contra Fund",
    "latest_date": "2026-04-23",
    "return_1d": -0.7,
    "return_1w": 0.52,
    "return_1m": 9.03,
    "return_3m": -1.48,
    "return_6m": -4.45,
    "return_1y": 3.19,
    "return_2y": 7.26,
    "return_3y": 19.81,
    "return_5y": 19.06,
    "return_10y": 17.23
  },
  {
    "category": "Aggressive Hybrid Fund",
    "latest_date": "2026-04-23",
    "return_1d": -0.61,
    "return_1w": 0.48,
    "return_1m": 8.07,
    "return_3m": 1.29,
    "return_6m": -2.32,
    "return_1y": 4.27,
    "return_2y": 7.52,
    "return_3y": 15.37,
    "return_5y": 14,
    "return_10y": 13.02
  },
  {
    "category": "Dynamic Asset Allocation or Balanced Advantage",
    "latest_date": "2026-04-23",
    "return_1d": -0.54,
    "return_1w": 0.28,
    "return_1m": 5.81,
    "return_3m": 0.57,
    "return_6m": -1.46,
    "return_1y": 3.96,
    "return_2y": 6.34,
    "return_3y": 12.93,
    "return_5y": 11.17,
    "return_10y": 11.62
  },
  {
    "category": "Multi Asset Allocation",
    "latest_date": "2026-04-23",
    "return_1d": -0.49,
    "return_1w": 0.33,
    "return_1m": 7.58,
    "return_3m": 0.09,
    "return_6m": 4.34,
    "return_1y": 14.92,
    "return_2y": 13.48,
    "return_3y": 19.24,
    "return_5y": 16.93,
    "return_10y": 14.18
  }
]
